.gitignore
CHANGES.rst
INSTALL.rst
README.rst
setup.cfg
setup.py
tests.py
docs/conf.py
docs/index.rst
pypsum/__init__.py
pypsum/application.py
pypsum/client.py
pypsum/settings.py
pypsum.egg-info/PKG-INFO
pypsum.egg-info/SOURCES.txt
pypsum.egg-info/dependency_links.txt
pypsum.egg-info/requires.txt
pypsum.egg-info/top_level.txt
pypsum/templates/index.html
pypsum/templates/state.html