Metadata-Version: 1.0
Name: pypsum
Version: 0.3.0
Summary: A RESTfull Lorem Ipsum text generator
Home-page: http://projects.monkeython.com/pypsum/html
Author: Luca De Vitis
Author-email: luca@monkeython.com
License: UNKNOWN
Platform: UNKNOWN
Classifier: Development Status :: 3 - Alpha
Classifier: Intended Audience :: Developers
Classifier: License :: OSI Approved :: GNU General Public License (GPL)
Classifier: Operating System :: OS Independent
Classifier: Topic :: Internet :: WWW/HTTP
